Metadata-Version: 1.0
Name: dprofiler
Version: 0.1.0
Summary: decorator profiling tool
Home-page: https://github.com/disktnk/dprofiler
Author: Daisuke Tanaka
Author-email: duaipp@gmail.com
License: UNKNOWN
Platform: UNKNOWN
